<?xml version="1.0" encoding="UTF-8"?><activity> <info><id></id><name></name><antecedent></antecedent><behavior></behavior><consequence></consequence><nativeWidth>1024</nativeWidth><nativeHeight>768</nativeHeight><category> </category></info><resources><audio>patyaraujo1599315733007</audio><image>patyaraujo16015785427143</image><image>patyaraujo16015785427143</image><image>patyaraujo16015788465441</image><image>patyaraujo16015789393616</image></resources><code><instruction><type>Prompt</type><position>0</position><next>1</next><description>Exibe estímulos (vídeo, texto, áudio, imagem).</description><editable>true</editable><data><showTime>3</showTime><clickToFinish>false</clickToFinish><audio><isClickable>true</isClickable><isDraggable>undefined</isDraggable><audioID>patyaraujo1599315733007</audioID><localID>1601593768127</localID><autoplay>true</autoplay><repeat>false</repeat><numberOfRepeats>0</numberOfRepeats><renderIcon>false</renderIcon><imageX>10</imageX><imageY>10</imageY></audio></data></instruction><instruction><type>SelectImage</type><position>1</position><next>-1</next><description>Apresenta estímulos e permite ao estudante selecionar um</description><editable>true</editable><data><expectedImage>1601593810991</expectedImage><model>1601593791290</model><onCorrect>undefined</onCorrect><onWrong>undefined</onWrong><image><imageID>patyaraujo16015785427143</imageID><isClickable>true</isClickable><isDraggable>true</isDraggable><imageWidth>243</imageWidth><imageHeight>226</imageHeight><imageX>273</imageX><imageY>9</imageY><localID>1601593791290</localID><containerID>null</containerID><dragAndAssociate>true</dragAndAssociate><fullContainer>false</fullContainer></image><image><imageID>patyaraujo16015785427143</imageID><isClickable>true</isClickable><isDraggable>true</isDraggable><imageWidth>247</imageWidth><imageHeight>228</imageHeight><imageX>277</imageX><imageY>309</imageY><localID>1601593810991</localID><containerID>null</containerID><dragAndAssociate>true</dragAndAssociate><fullContainer>false</fullContainer></image><image><imageID>patyaraujo16015788465441</imageID><isClickable>true</isClickable><isDraggable>true</isDraggable><imageWidth>215</imageWidth><imageHeight>230</imageHeight><imageX>20</imageX><imageY>306</imageY><localID>1601593823020</localID><containerID>null</containerID><dragAndAssociate>true</dragAndAssociate><fullContainer>false</fullContainer></image><image><imageID>patyaraujo16015789393616</imageID><isClickable>true</isClickable><isDraggable>true</isDraggable><imageWidth>214</imageWidth><imageHeight>262</imageHeight><imageX>579</imageX><imageY>286</imageY><localID>1601593836170</localID><containerID>null</containerID><dragAndAssociate>true</dragAndAssociate><fullContainer>false</fullContainer></image></data></instruction></code></activity>