<?xml version="1.0" encoding="UTF-8"?><activity> <info><id>empty</id><name>name</name><antecedent></antecedent><behavior></behavior><consequence></consequence><nativeWidth>1024</nativeWidth><nativeHeight>768</nativeHeight><category> empty </category></info><resources><image>mu15834169960874</image><audio>vivianemon15875806300218</audio></resources><code><instruction><type>Prompt</type><position>0</position><next>-1</next><description>Exibe estímulos (vídeo, texto, áudio, imagem).</description><editable>true</editable><data><showTime>5</showTime><image><imageID>mu15834169960874</imageID><isClickable>true</isClickable><isDraggable>false</isDraggable><imageWidth>469</imageWidth><imageHeight>470</imageHeight><imageX>159</imageX><imageY>121</imageY><localID>1586890413206</localID><containerID>true</containerID><dragAndAssociate>[object Object]</dragAndAssociate></image><audio><isClickable>true</isClickable><isDraggable>undefined</isDraggable><audioID>vivianemon15875806300218</audioID><localID>1587580652774</localID><autoplay>true</autoplay><repeat>false</repeat><numberOfRepeats>0</numberOfRepeats><renderIcon>false</renderIcon><imageX>10</imageX><imageY>10</imageY></audio><text><text>ACERTOU</text><textX>103</textX><textY>-2</textY><fontSize>120</fontSize><fontColor>#000000</fontColor><localID>1586890424696</localID></text></data></instruction></code></activity>