<?xml version="1.0" encoding="UTF-8"?><activity> <info><id></id><name></name><antecedent></antecedent><behavior></behavior><consequence></consequence><nativeWidth>1024</nativeWidth><nativeHeight>768</nativeHeight><category> </category></info><resources><image>vivianemon15881806787637</image><image>vivianemon15881807588931</image><image>vivianemon1588180741475</image><image>vivianemon15881807010181</image><image>vivianemon15881807736277</image><image>vivianemon15881807257985</image><audio>vivianemon15916348997466</audio></resources><code><instruction><type>PositionImages</type><position>0</position><next>-1</next><description>Permite arrastar e agrupar imagens.</description><editable>true</editable><data><positions0>1588137618413</positions0><positions1>1588137662436</positions1><positions2>1588137701983</positions2><moreThanOneStimulusInContainer>false</moreThanOneStimulusInContainer><allowWrongStimuliInContainer>true</allowWrongStimuliInContainer><audioInstruction>1591636547114</audioInstruction><finishButton>1570017005838</finishButton><image><imageID>vivianemon15881806787637</imageID><isClickable>false</isClickable><isDraggable>false</isDraggable><imageWidth>200.0078125</imageWidth><imageHeight>146.5078125</imageHeight><imageX>100.00390625</imageX><imageY>0.25390625</imageY><localID>1588137618413</localID><containerID>true</containerID><dragAndAssociate>[object Object]</dragAndAssociate><fullContainer>false</fullContainer></image><image><imageID>vivianemon15881807588931</imageID><isClickable>false</isClickable><isDraggable>false</isDraggable><imageWidth>199.00390625</imageWidth><imageHeight>145.25390625</imageHeight><imageX>101.0078125</imageX><imageY>228.5078125</imageY><localID>1588137662436</localID><containerID>true</containerID><dragAndAssociate>[object Object]</dragAndAssociate><fullContainer>false</fullContainer></image><image><imageID>vivianemon1588180741475</imageID><isClickable>false</isClickable><isDraggable>false</isDraggable><imageWidth>201.00390625</imageWidth><imageHeight>146.25390625</imageHeight><imageX>99.01171875</imageX><imageY>452.76171875</imageY><localID>1588137701983</localID><containerID>true</containerID><dragAndAssociate>[object Object]</dragAndAssociate><fullContainer>false</fullContainer></image><image><imageID>vivianemon15881807010181</imageID><isClickable>true</isClickable><isDraggable>true</isDraggable><imageWidth>199.00390625</imageWidth><imageHeight>144.25390625</imageHeight><imageX>499.0078125</imageX><imageY>1.5078125</imageY><localID>1588137778240</localID><containerID>1588137618413</containerID><dragAndAssociate>true</dragAndAssociate><fullContainer>false</fullContainer></image><image><imageID>vivianemon15881807736277</imageID><isClickable>true</isClickable><isDraggable>true</isDraggable><imageWidth>194.00390625</imageWidth><imageHeight>138.25390625</imageHeight><imageX>503.0078125</imageX><imageY>459.5078125</imageY><localID>1588137807548</localID><containerID>1588137662436</containerID><dragAndAssociate>true</dragAndAssociate><fullContainer>false</fullContainer></image><image><imageID>vivianemon15881807257985</imageID><isClickable>true</isClickable><isDraggable>true</isDraggable><imageWidth>197.00390625</imageWidth><imageHeight>141.25390625</imageHeight><imageX>502.01953125</imageX><imageY>235.26953125</imageY><localID>1588137844300</localID><containerID>1588137701983</containerID><dragAndAssociate>true</dragAndAssociate><fullContainer>false</fullContainer></image><audio><isClickable>true</isClickable><isDraggable>undefined</isDraggable><audioID>vivianemon15916348997466</audioID><localID>1591636547114</localID><autoplay>true</autoplay><repeat>false</repeat><numberOfRepeats>0</numberOfRepeats><renderIcon>false</renderIcon><imageX>10</imageX><imageY>10</imageY></audio></data></instruction></code></activity>