<?xml version="1.0" encoding="UTF-8"?><activity> <info><id></id><name></name><antecedent></antecedent><behavior></behavior><consequence></consequence><nativeWidth>1024</nativeWidth><nativeHeight>768</nativeHeight><category> </category></info><resources><image>vivianemon15880270470625</image><image>vivianemon1588026817415</image><image>vivianemon15880270470625</image><image>vivianemon1588026817415</image><audio>vivianemon15916348762576</audio><image>vivianemon1588026907662</image><image>vivianemon1588026907662</image></resources><code><instruction><type>PositionImages</type><position>0</position><next>-1</next><description>Permite arrastar e agrupar imagens.</description><editable>true</editable><data><positions0>1588095319801</positions0><positions1>1588097646425</positions1><positions2>1593629034550</positions2><moreThanOneStimulusInContainer>false</moreThanOneStimulusInContainer><allowWrongStimuliInContainer>true</allowWrongStimuliInContainer><audioInstruction>1591640907039</audioInstruction><finishButton>1570017005838</finishButton><image><imageID>vivianemon15880270470625</imageID><isClickable>false</isClickable><isDraggable>false</isDraggable><imageWidth>100</imageWidth><imageHeight>97</imageHeight><imageX>98.00390625</imageX><imageY>-3.74609375</imageY><localID>1588095319801</localID><containerID>true</containerID><dragAndAssociate>[object Object]</dragAndAssociate><fullContainer>false</fullContainer></image><image><imageID>vivianemon1588026817415</imageID><isClickable>false</isClickable><isDraggable>false</isDraggable><imageWidth>98</imageWidth><imageHeight>92</imageHeight><imageX>101.015625</imageX><imageY>507.015625</imageY><localID>1588097646425</localID><containerID>true</containerID><dragAndAssociate>[object Object]</dragAndAssociate><fullContainer>false</fullContainer></image><image><imageID>vivianemon15880270470625</imageID><isClickable>true</isClickable><isDraggable>true</isDraggable><imageWidth>98.00390625</imageWidth><imageHeight>95.25390625</imageHeight><imageX>600.015625</imageX><imageY>257.015625</imageY><localID>1588097672110</localID><containerID>1588095319801</containerID><dragAndAssociate>true</dragAndAssociate><fullContainer>false</fullContainer></image><image><imageID>vivianemon1588026817415</imageID><isClickable>true</isClickable><isDraggable>true</isDraggable><imageWidth>95</imageWidth><imageHeight>89</imageHeight><imageX>601.01171875</imageX><imageY>0.76171875</imageY><localID>1588097760635</localID><containerID>1588097646425</containerID><dragAndAssociate>true</dragAndAssociate><fullContainer>false</fullContainer></image><audio><isClickable>true</isClickable><isDraggable>undefined</isDraggable><audioID>vivianemon15916348762576</audioID><localID>1591640907039</localID><autoplay>true</autoplay><repeat>false</repeat><numberOfRepeats>0</numberOfRepeats><renderIcon>false</renderIcon><imageX>10</imageX><imageY>10</imageY></audio><image><imageID>vivianemon1588026907662</imageID><isClickable>true</isClickable><isDraggable>true</isDraggable><imageWidth>99.00390625</imageWidth><imageHeight>101.25390625</imageHeight><imageX>99.015625</imageX><imageY>249.015625</imageY><localID>1593629034550</localID><containerID>null</containerID><dragAndAssociate>false</dragAndAssociate><fullContainer>false</fullContainer></image><image><imageID>vivianemon1588026907662</imageID><isClickable>true</isClickable><isDraggable>true</isDraggable><imageWidth>94.02734375</imageWidth><imageHeight>90.77734375</imageHeight><imageX>603.046875</imageX><imageY>508.046875</imageY><localID>1593629070158</localID><containerID>1593629034550</containerID><dragAndAssociate>true</dragAndAssociate><fullContainer>false</fullContainer></image></data></instruction></code></activity>