<?xml version="1.0" encoding="UTF-8"?><activity> <info><id></id><name></name><antecedent></antecedent><behavior></behavior><consequence></consequence><nativeWidth>1024</nativeWidth><nativeHeight>768</nativeHeight><category> </category></info><resources><image>patyaraujo15955263268262</image><audio>patyaraujo15962203637663</audio><image>patyaraujo15962214100485</image><image>patyaraujo15955264313774</image><image>patyaraujo15955263268262</image></resources><code><instruction><type>Prompt</type><position>0</position><next>1</next><description>Exibe estímulos (vídeo, texto, áudio, imagem).</description><editable>true</editable><data><showTime>10</showTime><clickToFinish>false</clickToFinish><image><imageID>patyaraujo15955263268262</imageID><isClickable>true</isClickable><isDraggable>false</isDraggable><imageWidth>313</imageWidth><imageHeight>313</imageHeight><imageX>210</imageX><imageY>126</imageY><localID>1597577136587</localID><containerID>null</containerID><dragAndAssociate>true</dragAndAssociate><fullContainer>false</fullContainer></image><audio><isClickable>true</isClickable><isDraggable>undefined</isDraggable><audioID>patyaraujo15962203637663</audioID><localID>1597577121984</localID><autoplay>true</autoplay><repeat>false</repeat><numberOfRepeats>0</numberOfRepeats><renderIcon>false</renderIcon><imageX>10</imageX><imageY>10</imageY></audio></data></instruction><instruction><type>SelectImage</type><position>1</position><next>-1</next><description>Apresenta estímulos e permite ao estudante selecionar um</description><editable>true</editable><data><expectedImage>1597577230871</expectedImage><model>null</model><onCorrect>undefined</onCorrect><onWrong>undefined</onWrong><image><imageID>patyaraujo15962214100485</imageID><isClickable>true</isClickable><isDraggable>false</isDraggable><imageWidth>473</imageWidth><imageHeight>419</imageHeight><imageX>158</imageX><imageY>73</imageY><localID>1597577183121</localID><containerID>null</containerID><dragAndAssociate>true</dragAndAssociate><fullContainer>false</fullContainer></image><image><imageID>patyaraujo15955264313774</imageID><isClickable>true</isClickable><isDraggable>false</isDraggable><imageWidth>257</imageWidth><imageHeight>267</imageHeight><imageX>546</imageX><imageY>164</imageY><localID>1597577191537</localID><containerID>null</containerID><dragAndAssociate>true</dragAndAssociate><fullContainer>false</fullContainer></image><image><imageID>patyaraujo15955263268262</imageID><isClickable>true</isClickable><isDraggable>false</isDraggable><imageWidth>269</imageWidth><imageHeight>278</imageHeight><imageX>-7</imageX><imageY>157</imageY><localID>1597577230871</localID><containerID>null</containerID><dragAndAssociate>true</dragAndAssociate><fullContainer>false</fullContainer></image></data></instruction></code></activity>