<?xml version="1.0" encoding="UTF-8"?><activity> <info><id>empty</id><name>name</name><antecedent></antecedent><behavior></behavior><consequence></consequence><nativeWidth>1024</nativeWidth><nativeHeight>768</nativeHeight><category> empty </category></info><resources><image>kesia1588821228661</image><audio>kesia15888787607199</audio><image>kesia15888209059926</image><image>kesia15888211445565</image></resources><code><instruction><type>SelectImage</type><position>0</position><next>1</next><description>Apresenta estímulos e permite ao estudante selecionar um</description><editable>true</editable><data><expectedImage>1588892817786</expectedImage><model>1588889201621</model><onCorrect>1</onCorrect><onWrong>1</onWrong><image><imageID>kesia1588821228661</imageID><isClickable>true</isClickable><isDraggable>false</isDraggable><imageWidth>313</imageWidth><imageHeight>288</imageHeight><imageX>310</imageX><imageY>145</imageY><localID>1588892817786</localID><containerID>true</containerID><dragAndAssociate>[object Object]</dragAndAssociate></image><audio><isClickable>false</isClickable><isDraggable>undefined</isDraggable><audioID>kesia15888787607199</audioID><localID>1588889201621</localID><autoplay>true</autoplay><repeat>false</repeat><numberOfRepeats>0</numberOfRepeats><renderIcon>false</renderIcon><imageX>10</imageX><imageY>10</imageY></audio><image><imageID>kesia15888209059926</imageID><isClickable>true</isClickable><isDraggable>true</isDraggable><imageWidth>283.03125</imageWidth><imageHeight>312.0625</imageHeight><imageX>58.03125</imageX><imageY>129.0625</imageY><localID>1589324608678</localID><containerID>true</containerID><dragAndAssociate>[object Object]</dragAndAssociate></image><image><imageID>kesia15888211445565</imageID><isClickable>true</isClickable><isDraggable>true</isDraggable><imageWidth>290.015625</imageWidth><imageHeight>303.53125</imageHeight><imageX>545.03125</imageX><imageY>139.0625</imageY><localID>1589324646418</localID><containerID>true</containerID><dragAndAssociate>[object Object]</dragAndAssociate></image></data></instruction><instruction><type>End</type><position>1</position><next>-1</next><description>Finaliza a Atividade</description><editable>false</editable><data/></instruction></code></activity>