<?xml version="1.0" encoding="UTF-8"?><activity> <info><id></id><name></name><antecedent></antecedent><behavior></behavior><consequence></consequence><nativeWidth>1024</nativeWidth><nativeHeight>768</nativeHeight><category> </category></info><resources><image>maerciomaia1597858400836</image><image>maerciomaia15995773384519</image><image>maerciomaia159957737597</image><image>maerciomaia15978582862104</image><image>maerciomaia15978585339744</image><image>maerciomaia15995774744436</image><audio>maerciomaia15995779276541</audio></resources><code><instruction><type>PositionImages</type><position>0</position><next>-1</next><description>Permite arrastar e agrupar imagens.</description><editable>true</editable><data><positions0>1599577331623</positions0><positions1>1599577361321</positions1><positions2>1599577459818</positions2><moreThanOneStimulusInContainer>true</moreThanOneStimulusInContainer><allowWrongStimuliInContainer>true</allowWrongStimuliInContainer><audioInstruction>1599578623381</audioInstruction><finishButton>1570017005838</finishButton><image><imageID>maerciomaia1597858400836</imageID><isClickable>true</isClickable><isDraggable>true</isDraggable><imageWidth>199</imageWidth><imageHeight>193</imageHeight><imageX>-3</imageX><imageY>1</imageY><localID>1599577289924</localID><containerID>1599577459818</containerID><dragAndAssociate>true</dragAndAssociate><fullContainer>false</fullContainer></image><image><imageID>maerciomaia15995773384519</imageID><isClickable>false</isClickable><isDraggable>false</isDraggable><imageWidth>197</imageWidth><imageHeight>198</imageHeight><imageX>302</imageX><imageY>0</imageY><localID>1599577331623</localID><containerID>null</containerID><dragAndAssociate>false</dragAndAssociate><fullContainer>false</fullContainer></image><image><imageID>maerciomaia159957737597</imageID><isClickable>false</isClickable><isDraggable>false</isDraggable><imageWidth>193</imageWidth><imageHeight>193</imageHeight><imageX>603</imageX><imageY>4</imageY><localID>1599577361321</localID><containerID>null</containerID><dragAndAssociate>false</dragAndAssociate><fullContainer>false</fullContainer></image><image><imageID>maerciomaia15978582862104</imageID><isClickable>true</isClickable><isDraggable>true</isDraggable><imageWidth>199</imageWidth><imageHeight>196</imageHeight><imageX>0</imageX><imageY>300</imageY><localID>1599577382231</localID><containerID>1599577331623</containerID><dragAndAssociate>true</dragAndAssociate><fullContainer>false</fullContainer></image><image><imageID>maerciomaia15978585339744</imageID><isClickable>true</isClickable><isDraggable>true</isDraggable><imageWidth>195</imageWidth><imageHeight>195</imageHeight><imageX>303</imageX><imageY>301</imageY><localID>1599577418392</localID><containerID>1599577361321</containerID><dragAndAssociate>true</dragAndAssociate><fullContainer>false</fullContainer></image><image><imageID>maerciomaia15995774744436</imageID><isClickable>false</isClickable><isDraggable>false</isDraggable><imageWidth>193</imageWidth><imageHeight>195</imageHeight><imageX>603</imageX><imageY>303</imageY><localID>1599577459818</localID><containerID>null</containerID><dragAndAssociate>false</dragAndAssociate><fullContainer>false</fullContainer></image><audio><isClickable>true</isClickable><isDraggable>undefined</isDraggable><audioID>maerciomaia15995779276541</audioID><localID>1599578623381</localID><autoplay>true</autoplay><repeat>false</repeat><numberOfRepeats>0</numberOfRepeats><renderIcon>false</renderIcon><imageX>10</imageX><imageY>10</imageY></audio></data></instruction></code></activity>