<?xml version="1.0" encoding="UTF-8"?><activity> <info><id></id><name></name><antecedent></antecedent><behavior></behavior><consequence></consequence><nativeWidth>1024</nativeWidth><nativeHeight>768</nativeHeight><category> </category></info><resources><image>isabela15887716823681</image><image>isabela15887718865682</image><image>isabela1588771849301</image></resources><code><instruction><type>Prompt</type><position>0</position><next>1</next><description>Exibe estímulos (vídeo, texto, áudio, imagem).</description><editable>true</editable><data><showTime>2</showTime><image><imageID>isabela15887716823681</imageID><isClickable>true</isClickable><isDraggable>true</isDraggable><imageWidth>196</imageWidth><imageHeight>196</imageHeight><imageX>303</imageX><imageY>230.6666717529297</imageY><localID>1588791976354</localID><containerID>true</containerID><dragAndAssociate>[object Object]</dragAndAssociate></image></data></instruction><instruction><type>SelectImage</type><position>1</position><next>-1</next><description>Apresenta estímulos e permite ao estudante selecionar um</description><editable>true</editable><data><expectedImage>1588792280474</expectedImage><model>undefined</model><onCorrect>undefined</onCorrect><onWrong>undefined</onWrong><image><imageID>isabela15887718865682</imageID><isClickable>true</isClickable><isDraggable>true</isDraggable><imageWidth>196</imageWidth><imageHeight>196</imageHeight><imageX>27</imageX><imageY>199.8666948080063</imageY><localID>1588792095147</localID><containerID>true</containerID><dragAndAssociate>[object Object]</dragAndAssociate></image><image><imageID>isabela1588771849301</imageID><isClickable>true</isClickable><isDraggable>true</isDraggable><imageWidth>196</imageWidth><imageHeight>196</imageHeight><imageX>580</imageX><imageY>192.00003814697266</imageY><localID>1588792280474</localID><containerID>true</containerID><dragAndAssociate>[object Object]</dragAndAssociate></image></data></instruction></code></activity>