<?xml version="1.0" encoding="UTF-8"?><activity> <info><id>empty</id><name>name</name><antecedent></antecedent><behavior></behavior><consequence></consequence><nativeWidth>1024</nativeWidth><nativeHeight>768</nativeHeight><category> empty </category></info><resources><audio>veronicacasagrande16084140223434</audio><image>veronicacasagrande1607999061192</image><image>veronicacasagrande16084148845722</image><image>veronicacasagrande16079993074314</image></resources><code><instruction><type>SelectImage</type><position>0</position><next>1</next><description>Apresenta estímulos e permite ao estudante selecionar um</description><editable>true</editable><data><expectedImage>1608414889003</expectedImage><model>1608414851116</model><onCorrect>1</onCorrect><onWrong>1</onWrong><audio><isClickable>true</isClickable><isDraggable>undefined</isDraggable><audioID>veronicacasagrande16084140223434</audioID><localID>1608414851116</localID><autoplay>true</autoplay><repeat>false</repeat><numberOfRepeats>0</numberOfRepeats><renderIcon>false</renderIcon><imageX>307.0078125</imageX><imageY>12.5078125</imageY></audio><image><imageID>veronicacasagrande1607999061192</imageID><isClickable>true</isClickable><isDraggable>true</isDraggable><imageWidth>268.00390625</imageWidth><imageHeight>251.00390625</imageHeight><imageX>9.00390625</imageX><imageY>217.00390625</imageY><localID>1608414856068</localID><containerID>null</containerID><dragAndAssociate>true</dragAndAssociate><fullContainer>false</fullContainer></image><image><imageID>veronicacasagrande16084148845722</imageID><isClickable>true</isClickable><isDraggable>true</isDraggable><imageWidth>269.00390625</imageWidth><imageHeight>231.00390625</imageHeight><imageX>292.0078125</imageX><imageY>217.0078125</imageY><localID>1608414889003</localID><containerID>null</containerID><dragAndAssociate>true</dragAndAssociate><fullContainer>false</fullContainer></image><image><imageID>veronicacasagrande16079993074314</imageID><isClickable>true</isClickable><isDraggable>true</isDraggable><imageWidth>219.0078125</imageWidth><imageHeight>232.0078125</imageHeight><imageX>567.01171875</imageX><imageY>218.01171875</imageY><localID>1608414895354</localID><containerID>null</containerID><dragAndAssociate>true</dragAndAssociate><fullContainer>false</fullContainer></image></data></instruction><instruction><type>End</type><position>1</position><next>-1</next><description>Finaliza a Atividade</description><editable>false</editable><data/></instruction></code></activity>