<?xml version="1.0" encoding="UTF-8"?><activity> <info><id>empty</id><name>name</name><antecedent></antecedent><behavior></behavior><consequence></consequence><nativeWidth>1024</nativeWidth><nativeHeight>768</nativeHeight><category> empty </category></info><resources><image>kesia15881805621751</image><image>kesia15888208384337</image><image>kesia15888207837303</image><image>veronicacasagrande16209347712109</image></resources><code><instruction><type>SelectImage</type><position>0</position><next>1</next><description>Apresenta estímulos e permite ao estudante selecionar um</description><editable>true</editable><data><expectedImage>1620936935114</expectedImage><model>1620936970785</model><onCorrect>1</onCorrect><onWrong>1</onWrong><image><imageID>kesia15881805621751</imageID><isClickable>true</isClickable><isDraggable>true</isDraggable><imageWidth>100</imageWidth><imageHeight>154</imageHeight><imageX>68.03124988079071</imageX><imageY>294.69789123535156</imageY><localID>1620936929109</localID><containerID>null</containerID><dragAndAssociate>true</dragAndAssociate><fullContainer>false</fullContainer></image><image><imageID>kesia15888208384337</imageID><isClickable>true</isClickable><isDraggable>true</isDraggable><imageWidth>138.01041662693024</imageWidth><imageHeight>187.5659637451172</imageHeight><imageX>266.0312498807907</imageX><imageY>295.69789123535156</imageY><localID>1620936935114</localID><containerID>null</containerID><dragAndAssociate>true</dragAndAssociate><fullContainer>false</fullContainer></image><image><imageID>kesia15888207837303</imageID><isClickable>true</isClickable><isDraggable>true</isDraggable><imageWidth>163.01041662693024</imageWidth><imageHeight>172.5659637451172</imageHeight><imageX>521.0312498807907</imageX><imageY>292.69789123535156</imageY><localID>1620936940853</localID><containerID>null</containerID><dragAndAssociate>true</dragAndAssociate><fullContainer>false</fullContainer></image><image><imageID>veronicacasagrande16209347712109</imageID><isClickable>true</isClickable><isDraggable>true</isDraggable><imageWidth>326.0208332538605</imageWidth><imageHeight>151.13192749023438</imageHeight><imageX>202.04166650772095</imageX><imageY>77.26385498046875</imageY><localID>1620936970785</localID><containerID>null</containerID><dragAndAssociate>true</dragAndAssociate><fullContainer>false</fullContainer></image></data></instruction><instruction><type>End</type><position>1</position><next>-1</next><description>Finaliza a Atividade</description><editable>false</editable><data/></instruction></code></activity>